pansync/__init__.py
pansync/cli/__init__.py
pansync/cli/main.py
pansync/config/__init__.py
pansync/config/client_manager.py
pansync/config/config_manager.py
pansync/core/__init__.py
pansync/core/file_manager.py
pansync/core/index_manager.py
pansync/core/lock_manager.py
pansync/core/sync_engine.py
pansync/utils/__init__.py
pansync/utils/file_utils.py
pansync/utils/hash_utils.py
pansync/utils/network_utils.py
pansync/utils/time_utils.py
pansync-0.1.0.dist-info/licenses/LICENSE
pansync-0.1.0.dist-info/METADATA
pansync-0.1.0.dist-info/WHEEL
pansync-0.1.0.dist-info/entry_points.txt
pansync-0.1.0.dist-info/top_level.txt
pansync-0.1.0.dist-info/RECORD
