Metadata-Version: 2.4
Name: pansync
Version: 0.1.0
Summary: 百度网盘多客户端同步工具
Home-page: https://github.com/username/pansync
Author: PanSync Team
Author-email: PanSync Team <pansync@example.com>
Project-URL: Homepage, https://github.com/username/pansync
Project-URL: Repository, https://github.com/username/pansync
Project-URL: Issues, https://github.com/username/pansync/issues
Classifier: Development Status :: 3 - Alpha
Classifier: Intended Audience :: End Users/Desktop
Classifier: License :: OSI Approved :: MIT License
Classifier: Operating System :: OS Independent
Classifier: Programming Language :: Python :: 3
Classifier: Programming Language :: Python :: 3.8
Classifier: Programming Language :: Python :: 3.9
Classifier: Programming Language :: Python :: 3.10
Classifier: Programming Language :: Python :: 3.11
Requires-Python: >=3.8
License-File: LICENSE
Requires-Dist: bypy>=1.8.0
Requires-Dist: PyYAML>=6.0
Requires-Dist: requests>=2.28.0
Requires-Dist: psutil>=5.9.0
Requires-Dist: click>=8.1.0
Requires-Dist: colorama>=0.4.6
Requires-Dist: cryptography>=41.0.0
Requires-Dist: loguru>=0.7.0
Requires-Dist: pytz>=2023.3
Requires-Dist: python-dateutil>=2.8.2
Requires-Dist: watchdog>=3.0.0
Requires-Dist: tqdm>=4.66.0
Requires-Dist: toml>=0.10.2
Requires-Dist: urllib3>=2.0.0
Provides-Extra: dev
Requires-Dist: pytest>=7.4.0; extra == "dev"
Requires-Dist: pytest-cov>=4.1.0; extra == "dev"
Requires-Dist: black>=23.7.0; extra == "dev"
Requires-Dist: flake8>=6.0.0; extra == "dev"
Requires-Dist: mypy>=1.5.0; extra == "dev"
Dynamic: author
Dynamic: home-page
Dynamic: license-file
Dynamic: requires-python
